aliyunsdkaicontent/__init__.py
aliyunsdkaicontent/request/__init__.py
aliyunsdkaicontent/request/v20240611/AliyunConsoleOpenApiQueryAliyunConsoleServcieListRequest.py
aliyunsdkaicontent/request/v20240611/Personalizedtxt2imgAddInferenceJobRequest.py
aliyunsdkaicontent/request/v20240611/Personalizedtxt2imgAddModelTrainJobRequest.py
aliyunsdkaicontent/request/v20240611/Personalizedtxt2imgQueryImageAssetRequest.py
aliyunsdkaicontent/request/v20240611/Personalizedtxt2imgQueryInferenceJobInfoRequest.py
aliyunsdkaicontent/request/v20240611/Personalizedtxt2imgQueryModelTrainJobListRequest.py
aliyunsdkaicontent/request/v20240611/Personalizedtxt2imgQueryModelTrainStatusRequest.py
aliyunsdkaicontent/request/v20240611/__init__.py
aliyun_python_sdk_aicontent-1.0.1.dist-info/LICENSE
aliyun_python_sdk_aicontent-1.0.1.dist-info/METADATA
aliyun_python_sdk_aicontent-1.0.1.dist-info/WHEEL
aliyun_python_sdk_aicontent-1.0.1.dist-info/top_level.txt
aliyun_python_sdk_aicontent-1.0.1.dist-info/RECORD
